arthemis_tts/__init__.py
arthemis_tts/audio_processing.py
arthemis_tts/config.py
arthemis_tts/text_processing.py
arthemis_tts/tts.py
arthemis_tts/utils.py
arthemis_tts-0.1.2.dist-info/licenses/LICENSE
arthemis_tts-0.1.2.dist-info/METADATA
arthemis_tts-0.1.2.dist-info/WHEEL
arthemis_tts-0.1.2.dist-info/top_level.txt
arthemis_tts-0.1.2.dist-info/RECORD
