Metadata-Version: 2.4
Name: arthemis-tts
Version: 0.1.2
Summary: A simple transformer-based text-to-speech library
Home-page: https://github.com/yourusername/arthemis-tts
Author: Harish Santhnakakshmi Ganesan
Author-email: harishsg99@gmail.com
Project-URL: Bug Reports, https://github.com/yourusername/arthemis-tts/issues
Project-URL: Source, https://github.com/yourusername/arthemis-tts
Project-URL: Documentation, https://github.com/yourusername/arthemis-tts#readme
Keywords: text-to-speech,tts,transformer,neural,speech synthesis
Classifier: Development Status :: 3 - Alpha
Classifier: Intended Audience :: Developers
Classifier: Intended Audience :: Science/Research
Classifier: License :: OSI Approved :: MIT License
Classifier: Operating System :: OS Independent
Classifier: Programming Language :: Python :: 3
Classifier: Programming Language :: Python :: 3.7
Classifier: Programming Language :: Python :: 3.8
Classifier: Programming Language :: Python :: 3.9
Classifier: Programming Language :: Python :: 3.10
Classifier: Topic :: Multimedia :: Sound/Audio :: Speech
Classifier: Topic :: Scientific/Engineering :: Artificial Intelligence
Requires-Python: >=3.7
License-File: LICENSE
Requires-Dist: torch>=1.9.0
Requires-Dist: torchaudio>=0.9.0
Requires-Dist: numpy>=1.19.0
Requires-Dist: pandas>=1.2.0
Requires-Dist: tqdm>=4.60.0
Requires-Dist: pydub>=0.25.0
Provides-Extra: dev
Requires-Dist: pytest>=6.0; extra == "dev"
Requires-Dist: black>=21.0; extra == "dev"
Requires-Dist: flake8>=3.9; extra == "dev"
Dynamic: author
Dynamic: author-email
Dynamic: classifier
Dynamic: description
Dynamic: description-content-type
Dynamic: home-page
Dynamic: keywords
Dynamic: license-file
Dynamic: project-url
Dynamic: provides-extra
Dynamic: requires-dist
Dynamic: requires-python
Dynamic: summary
